[{"metadata":{"result_type":"recent","iso_language_code":"en"},"in_reply_to_status_id_str":null,"in_reply_to_status_id":null,"created_at":"Fri Jan 31 21:39:44 +0000 2020","in_reply_to_user_id_str":null,"source":"<a href=\"https://mobile.twitter.com\" rel=\"nofollow\">Twitter Web App<\/a>","retweeted_status":{"metadata":{"result_type":"recent","iso_language_code":"en"},"quoted_status":{"metadata":{"result_type":"recent","iso_language_code":"en"},"in_reply_to_status_id_str":null,"in_reply_to_status_id":null,"coordinates":null,"created_at":"Fri Jan 31 06:10:40 +0000 2020","truncated":false,"in_reply_to_user_id_str":null,"source":"<a href=\"https://mobile.twitter.com\" rel=\"nofollow\">Twitter Web App<\/a>","retweet_count":199,"retweeted":false,"geo":null,"in_reply_to_screen_name":null,"is_quote_status":false,"entities":{"urls":[],"hashtags":[],"user_mentions":[],"symbols":[]},"id_str":"1223126433293189120","in_reply_to_user_id":null,"favorite_count":1727,"id":1223126433293189120,"text":"Interviewer: \"I see here there's a 2 year gap in your resume, what were you doing?\"\n\nWrong answers only.","place":null,"contributors":null,"lang":"en","user":{"utc_offset":null,"friends_count":905,"profile_image_url_https":"https://pbs.twimg.com/profile_images/1138248155340955648/v-9Te9qN_normal.png","listed_count":164,"profile_background_image_url":"http://abs.twimg.com/images/themes/theme17/bg.gif","default_profile_image":false,"favourites_count":5997,"description":"Break. Analyze. Repeat. Red Team Manager at Target. Formerly IOActive, BT Americas. Opinions do not reflect those of my employer. He/him.","created_at":"Sun Oct 10 18:19:12 +0000 2010","is_translator":false,"profile_background_image_url_https":"https://abs.twimg.com/images/themes/theme17/bg.gif","protected":false,"screen_name":"redteamwrangler","id_str":"200950703","profile_link_color":"9266CC","is_translation_enabled":false,"translator_type":"none","id":200950703,"geo_enabled":false,"profile_background_color":"000000","lang":null,"has_extended_profile":false,"profile_sidebar_border_color":"000000","profile_text_color":"000000","verified":false,"profile_image_url":"http://pbs.twimg.com/profile_images/1138248155340955648/v-9Te9qN_normal.png","time_zone":null,"url":null,"contributors_enabled":false,"profile_background_tile":false,"profile_banner_url":"https://pbs.twimg.com/profile_banners/200950703/1541397724","entities":{"description":{"urls":[]}},"statuses_count":2961,"follow_request_sent":false,"followers_count":4495,"profile_use_background_image":false,"default_profile":false,"following":false,"name":"Ryan O'Horo","location":"Minneapolis, MN","profile_sidebar_fill_color":"000000","notifications":false},"favorited":false},"in_reply_to_status_id_str":null,"in_reply_to_status_id":null,"created_at":"Fri Jan 31 08:12:39 +0000 2020","in_reply_to_user_id_str":null,"source":"<a href=\"http://twitter.com/download/android\" rel=\"nofollow\">Twitter for Android<\/a>","quoted_status_id":1223126433293189120,"retweet_count":67,"retweeted":false,"geo":null,"in_reply_to_screen_name":null,"is_quote_status":true,"id_str":"1223157129172807681","in_reply_to_user_id":null,"favorite_count":742,"id":1223157129172807681,"text":"waiting on an Xcode build to complete 😫 https://t.co/3PVp3tz8rw","place":null,"lang":"en","favorited":false,"possibly_sensitive":false,"coordinates":null,"truncated":false,"entities":{"urls":[{"display_url":"twitter.com/redteamwrangle\u2026","indices":[40,63],"expanded_url":"https://twitter.com/redteamwrangler/status/1223126433293189120","url":"https://t.co/3PVp3tz8rw"}],"hashtags":[],"user_mentions":[],"symbols":[]},"quoted_status_id_str":"1223126433293189120","contributors":null,"user":{"utc_offset":null,"friends_count":512,"profile_image_url_https":"https://pbs.twimg.com/profile_images/1141742921240104961/ylpMiYrr_normal.jpg","listed_count":665,"profile_background_image_url":"http://abs.twimg.com/images/themes/theme3/bg.gif","default_profile_image":false,"favourites_count":119856,"description":"Senior Developer Advocate @Applitools | Director of @TestAutomationU | International Keynote Speaker | Master Inventor | Formerly @Twitter & @IBM","created_at":"Fri Dec 19 22:13:09 +0000 2014","is_translator":false,"profile_background_image_url_https":"https://abs.twimg.com/images/themes/theme3/bg.gif","protected":false,"screen_name":"techgirl1908","id_str":"2932738834","profile_link_color":"E81C4F","is_translation_enabled":false,"translator_type":"regular","id":2932738834,"geo_enabled":true,"profile_background_color":"000000","lang":null,"has_extended_profile":false,"profile_sidebar_border_color":"000000","profile_text_color":"000000","verified":false,"profile_image_url":"http://pbs.twimg.com/profile_images/1141742921240104961/ylpMiYrr_normal.jpg","time_zone":null,"url":"https://t.co/Y59L5yK5Ct","contributors_enabled":false,"profile_background_tile":false,"profile_banner_url":"https://pbs.twimg.com/profile_banners/2932738834/1470363100","entities":{"description":{"urls":[]},"url":{"urls":[{"display_url":"angiejones.tech","indices":[0,23],"expanded_url":"http://angiejones.tech","url":"https://t.co/Y59L5yK5Ct"}]}},"statuses_count":33473,"follow_request_sent":false,"followers_count":27988,"profile_use_background_image":false,"default_profile":false,"following":false,"name":"Angie Jones","location":"San Francisco, CA","profile_sidebar_fill_color":"000000","notifications":false}},"quoted_status_id":1223126433293189120,"retweet_count":67,"retweeted":false,"geo":null,"in_reply_to_screen_name":null,"is_quote_status":true,"id_str":"1223360237752803333","in_reply_to_user_id":null,"favorite_count":0,"id":1223360237752803333,"text":"RT @techgirl1908: waiting on an Xcode build to complete 😫 https://t.co/3PVp3tz8rw","place":null,"lang":"en","favorited":false,"possibly_sensitive":false,"coordinates":null,"truncated":false,"entities":{"urls":[{"display_url":"twitter.com/redteamwrangle\u2026","indices":[58,81],"expanded_url":"https://twitter.com/redteamwrangler/status/1223126433293189120","url":"https://t.co/3PVp3tz8rw"}],"hashtags":[],"user_mentions":[{"indices":[3,16],"screen_name":"techgirl1908","id_str":"2932738834","name":"Angie Jones","id":2932738834}],"symbols":[]},"quoted_status_id_str":"1223126433293189120","contributors":null,"user":{"utc_offset":null,"friends_count":695,"profile_image_url_https":"https://pbs.twimg.com/profile_images/2316539047/y13vrqqe257qh7h9erb9_normal.png","listed_count":243,"profile_background_image_url":"http://abs.twimg.com/images/themes/theme1/bg.png","default_profile_image":false,"favourites_count":28740,"description":"Professional Software Developer. Amateur Futurist and Chart Critic. Math Enthusiast. I write static code analysis tools and 1st drafts of blog posts. he/him","created_at":"Tue Jul 28 14:37:29 +0000 2009","is_translator":false,"profile_background_image_url_https":"https://abs.twimg.com/images/themes/theme1/bg.png","protected":false,"screen_name":"lizardbill","id_str":"60919433","profile_link_color":"0E6E20","is_translation_enabled":false,"translator_type":"none","id":60919433,"geo_enabled":true,"profile_background_color":"9AC295","lang":null,"has_extended_profile":false,"profile_sidebar_border_color":"C7EDCC","profile_text_color":"543920","verified":false,"profile_image_url":"http://pbs.twimg.com/profile_images/2316539047/y13vrqqe257qh7h9erb9_normal.png","time_zone":null,"url":"https://t.co/ZJdVLoKjKc","contributors_enabled":false,"profile_background_tile":false,"profile_banner_url":"https://pbs.twimg.com/profile_banners/60919433/1542989249","entities":{"description":{"urls":[]},"url":{"urls":[{"display_url":"BillTheLizard.blogspot.com","indices":[0,23],"expanded_url":"http://www.BillTheLizard.blogspot.com","url":"https://t.co/ZJdVLoKjKc"}]}},"statuses_count":19279,"follow_request_sent":false,"followers_count":5315,"profile_use_background_image":false,"default_profile":false,"following":false,"name":"Bill the Lizard","location":"Charlotte, NC USA","profile_sidebar_fill_color":"9DD4A9","notifications":false}}, {"metadata":{"result_type":"recent","iso_language_code":"en"},"in_reply_to_status_id_str":"1223334549410795520","in_reply_to_status_id":1223334549410795520,"coordinates":null,"created_at":"Fri Jan 31 20:26:39 +0000 2020","truncated":false,"in_reply_to_user_id_str":"977314361952866306","source":"<a href=\"https://mobile.twitter.com\" rel=\"nofollow\">Twitter Web App<\/a>","retweet_count":0,"retweeted":false,"geo":null,"in_reply_to_screen_name":"pekkagaiser","is_quote_status":false,"entities":{"urls":[],"hashtags":[],"user_mentions":[{"indices":[0,12],"screen_name":"pekkagaiser","id_str":"977314361952866306","name":"Pekka","id":977314361952866306}],"symbols":[]},"id_str":"1223341845574508553","in_reply_to_user_id":977314361952866306,"favorite_count":1,"id":1223341845574508553,"text":"@pekkagaiser 4 different units and 4 different baselines. Niiiiice.","place":null,"contributors":null,"lang":"en","user":{"utc_offset":null,"friends_count":695,"profile_image_url_https":"https://pbs.twimg.com/profile_images/2316539047/y13vrqqe257qh7h9erb9_normal.png","listed_count":243,"profile_background_image_url":"http://abs.twimg.com/images/themes/theme1/bg.png","default_profile_image":false,"favourites_count":28740,"description":"Professional Software Developer. Amateur Futurist and Chart Critic. Math Enthusiast. I write static code analysis tools and 1st drafts of blog posts. he/him","created_at":"Tue Jul 28 14:37:29 +0000 2009","is_translator":false,"profile_background_image_url_https":"https://abs.twimg.com/images/themes/theme1/bg.png","protected":false,"screen_name":"lizardbill","id_str":"60919433","profile_link_color":"0E6E20","is_translation_enabled":false,"translator_type":"none","id":60919433,"geo_enabled":true,"profile_background_color":"9AC295","lang":null,"has_extended_profile":false,"profile_sidebar_border_color":"C7EDCC","profile_text_color":"543920","verified":false,"profile_image_url":"http://pbs.twimg.com/profile_images/2316539047/y13vrqqe257qh7h9erb9_normal.png","time_zone":null,"url":"https://t.co/ZJdVLoKjKc","contributors_enabled":false,"profile_background_tile":false,"profile_banner_url":"https://pbs.twimg.com/profile_banners/60919433/1542989249","entities":{"description":{"urls":[]},"url":{"urls":[{"display_url":"BillTheLizard.blogspot.com","indices":[0,23],"expanded_url":"http://www.BillTheLizard.blogspot.com","url":"https://t.co/ZJdVLoKjKc"}]}},"statuses_count":19279,"follow_request_sent":false,"followers_count":5315,"profile_use_background_image":false,"default_profile":false,"following":false,"name":"Bill the Lizard","location":"Charlotte, NC USA","profile_sidebar_fill_color":"9DD4A9","notifications":false},"favorited":false}, {"metadata":{"result_type":"recent","iso_language_code":"en"},"in_reply_to_status_id_str":"1223334549410795520","in_reply_to_status_id":1223334549410795520,"coordinates":null,"created_at":"Fri Jan 31 19:58:15 +0000 2020","truncated":false,"in_reply_to_user_id_str":"977314361952866306","source":"<a href=\"https://mobile.twitter.com\" rel=\"nofollow\">Twitter Web App<\/a>","retweet_count":0,"retweeted":false,"geo":null,"in_reply_to_screen_name":"pekkagaiser","is_quote_status":false,"entities":{"urls":[],"hashtags":[],"user_mentions":[{"indices":[0,11],"screen_name":"lizardbill","id_str":"60919433","name":"Bill the Lizard","id":60919433}],"symbols":[]},"id_str":"1223334698417631233","in_reply_to_user_id":977314361952866306,"favorite_count":1,"id":1223334698417631233,"text":"@lizardbill As a graphic designer I have to say, I sort of dig it","place":null,"contributors":null,"lang":"en","user":{"utc_offset":null,"friends_count":436,"profile_image_url_https":"https://pbs.twimg.com/profile_images/1006818081862291459/vmM3KP5S_normal.jpg","listed_count":1,"profile_background_image_url":"http://abs.twimg.com/images/themes/theme1/bg.png","default_profile_image":false,"favourites_count":54754,"description":"🇩🇪🇫🇮, live in 🇪🇸🇮🇨. Anglophile 🇺🇸🇬🇧. WebDev, graphic design & an old off-the-grid house by ☀️, politics & culture during breaks, art & visual storytelling by 🌜.","created_at":"Fri Mar 23 22:41:16 +0000 2018","is_translator":false,"profile_background_image_url_https":"https://abs.twimg.com/images/themes/theme1/bg.png","protected":false,"screen_name":"pekkagaiser","id_str":"977314361952866306","profile_link_color":"336666","is_translation_enabled":false,"translator_type":"none","id":977314361952866306,"geo_enabled":false,"profile_background_color":"000000","lang":null,"has_extended_profile":false,"profile_sidebar_border_color":"000000","profile_text_color":"000000","verified":false,"profile_image_url":"http://pbs.twimg.com/profile_images/1006818081862291459/vmM3KP5S_normal.jpg","time_zone":null,"url":"https://t.co/Liir0lAVxY","contributors_enabled":false,"profile_background_tile":false,"profile_banner_url":"https://pbs.twimg.com/profile_banners/977314361952866306/1551776975","entities":{"description":{"urls":[]},"url":{"urls":[{"display_url":"pekka.net","indices":[0,23],"expanded_url":"http://www.pekka.net/","url":"https://t.co/Liir0lAVxY"}]}},"statuses_count":5665,"follow_request_sent":false,"followers_count":265,"profile_use_background_image":false,"default_profile":false,"following":false,"name":"Pekka","location":"Lanzarote, Canary Islands","profile_sidebar_fill_color":"000000","notifications":false},"favorited":false}, {"extended_entities":{"media":[{"display_url":"pic.twitter.com/P66CzHGGGM","indices":[41,64],"sizes":{"small":{"w":469,"h":680,"resize":"fit"},"large":{"w":499,"h":723,"resize":"fit"},"thumb":{"w":150,"h":150,"resize":"crop"},"medium":{"w":499,"h":723,"resize":"fit"}},"id_str":"1223334539914858496","expanded_url":"https://twitter.com/pekkagaiser/status/1223334549410795520/photo/1","media_url_https":"https://pbs.twimg.com/media/EPooSFUXUAABP6A.jpg","id":1223334539914858496,"type":"photo","media_url":"http://pbs.twimg.com/media/EPooSFUXUAABP6A.jpg","url":"https://t.co/P66CzHGGGM"}]},"metadata":{"result_type":"recent","iso_language_code":"en"},"in_reply_to_status_id_str":null,"in_reply_to_status_id":null,"created_at":"Fri Jan 31 19:57:39 +0000 2020","in_reply_to_user_id_str":null,"source":"<a href=\"https://mobile.twitter.com\" rel=\"nofollow\">Twitter Web App<\/a>","retweet_count":0,"retweeted":false,"geo":null,"in_reply_to_screen_name":null,"is_quote_status":false,"id_str":"1223334549410795520","in_reply_to_user_id":null,"favorite_count":3,"id":1223334549410795520,"text":"Presented to @lizardbill without comment https://t.co/P66CzHGGGM","place":null,"lang":"en","favorited":false,"possibly_sensitive":false,"coordinates":null,"truncated":false,"entities":{"urls":[],"hashtags":[],"media":[{"display_url":"pic.twitter.com/P66CzHGGGM","indices":[41,64],"sizes":{"small":{"w":469,"h":680,"resize":"fit"},"large":{"w":499,"h":723,"resize":"fit"},"thumb":{"w":150,"h":150,"resize":"crop"},"medium":{"w":499,"h":723,"resize":"fit"}},"id_str":"1223334539914858496","expanded_url":"https://twitter.com/pekkagaiser/status/1223334549410795520/photo/1","media_url_https":"https://pbs.twimg.com/media/EPooSFUXUAABP6A.jpg","id":1223334539914858496,"type":"photo","media_url":"http://pbs.twimg.com/media/EPooSFUXUAABP6A.jpg","url":"https://t.co/P66CzHGGGM"}],"user_mentions":[{"indices":[13,24],"screen_name":"lizardbill","id_str":"60919433","name":"Bill the Lizard","id":60919433}],"symbols":[]},"contributors":null,"user":{"utc_offset":null,"friends_count":436,"profile_image_url_https":"https://pbs.twimg.com/profile_images/1006818081862291459/vmM3KP5S_normal.jpg","listed_count":1,"profile_background_image_url":"http://abs.twimg.com/images/themes/theme1/bg.png","default_profile_image":false,"favourites_count":54754,"description":"🇩🇪🇫🇮, live in 🇪🇸🇮🇨. Anglophile 🇺🇸🇬🇧. WebDev, graphic design & an old off-the-grid house by ☀️, politics & culture during breaks, art & visual storytelling by 🌜.","created_at":"Fri Mar 23 22:41:16 +0000 2018","is_translator":false,"profile_background_image_url_https":"https://abs.twimg.com/images/themes/theme1/bg.png","protected":false,"screen_name":"pekkagaiser","id_str":"977314361952866306","profile_link_color":"336666","is_translation_enabled":false,"translator_type":"none","id":977314361952866306,"geo_enabled":false,"profile_background_color":"000000","lang":null,"has_extended_profile":false,"profile_sidebar_border_color":"000000","profile_text_color":"000000","verified":false,"profile_image_url":"http://pbs.twimg.com/profile_images/1006818081862291459/vmM3KP5S_normal.jpg","time_zone":null,"url":"https://t.co/Liir0lAVxY","contributors_enabled":false,"profile_background_tile":false,"profile_banner_url":"https://pbs.twimg.com/profile_banners/977314361952866306/1551776975","entities":{"description":{"urls":[]},"url":{"urls":[{"display_url":"pekka.net","indices":[0,23],"expanded_url":"http://www.pekka.net/","url":"https://t.co/Liir0lAVxY"}]}},"statuses_count":5665,"follow_request_sent":false,"followers_count":265,"profile_use_background_image":false,"default_profile":false,"following":false,"name":"Pekka","location":"Lanzarote, Canary Islands","profile_sidebar_fill_color":"000000","notifications":false}}, {"metadata":{"result_type":"recent","iso_language_code":"en"},"in_reply_to_status_id_str":null,"in_reply_to_status_id":null,"coordinates":null,"created_at":"Fri Jan 31 15:51:18 +0000 2020","truncated":false,"in_reply_to_user_id_str":null,"source":"<a href=\"https://mobile.twitter.com\" rel=\"nofollow\">Twitter Web App<\/a>","retweet_count":0,"retweeted":false,"geo":null,"in_reply_to_screen_name":null,"is_quote_status":false,"entities":{"urls":[],"hashtags":[],"user_mentions":[],"symbols":[]},"id_str":"1223272550815404035","in_reply_to_user_id":null,"favorite_count":7,"id":1223272550815404035,"text":"I decided to do a dry January this year, so naturally it's the longest January on record.","place":null,"contributors":null,"lang":"en","user":{"utc_offset":null,"friends_count":695,"profile_image_url_https":"https://pbs.twimg.com/profile_images/2316539047/y13vrqqe257qh7h9erb9_normal.png","listed_count":243,"profile_background_image_url":"http://abs.twimg.com/images/themes/theme1/bg.png","default_profile_image":false,"favourites_count":28740,"description":"Professional Software Developer. Amateur Futurist and Chart Critic. Math Enthusiast. I write static code analysis tools and 1st drafts of blog posts. he/him","created_at":"Tue Jul 28 14:37:29 +0000 2009","is_translator":false,"profile_background_image_url_https":"https://abs.twimg.com/images/themes/theme1/bg.png","protected":false,"screen_name":"lizardbill","id_str":"60919433","profile_link_color":"0E6E20","is_translation_enabled":false,"translator_type":"none","id":60919433,"geo_enabled":true,"profile_background_color":"9AC295","lang":null,"has_extended_profile":false,"profile_sidebar_border_color":"C7EDCC","profile_text_color":"543920","verified":false,"profile_image_url":"http://pbs.twimg.com/profile_images/2316539047/y13vrqqe257qh7h9erb9_normal.png","time_zone":null,"url":"https://t.co/ZJdVLoKjKc","contributors_enabled":false,"profile_background_tile":false,"profile_banner_url":"https://pbs.twimg.com/profile_banners/60919433/1542989249","entities":{"description":{"urls":[]},"url":{"urls":[{"display_url":"BillTheLizard.blogspot.com","indices":[0,23],"expanded_url":"http://www.BillTheLizard.blogspot.com","url":"https://t.co/ZJdVLoKjKc"}]}},"statuses_count":19279,"follow_request_sent":false,"followers_count":5315,"profile_use_background_image":false,"default_profile":false,"following":false,"name":"Bill the Lizard","location":"Charlotte, NC USA","profile_sidebar_fill_color":"9DD4A9","notifications":false},"favorited":false}, {"metadata":{"result_type":"recent","iso_language_code":"en"},"in_reply_to_status_id_str":"1223234297823408128","in_reply_to_status_id":1223234297823408128,"coordinates":null,"created_at":"Fri Jan 31 15:16:18 +0000 2020","truncated":false,"in_reply_to_user_id_str":"60919433","source":"<a href=\"http://twitter.com/download/iphone\" rel=\"nofollow\">Twitter for iPhone<\/a>","retweet_count":0,"retweeted":false,"geo":null,"in_reply_to_screen_name":"lizardbill","is_quote_status":false,"entities":{"urls":[],"hashtags":[],"user_mentions":[{"indices":[0,11],"screen_name":"lizardbill","id_str":"60919433","name":"Bill the Lizard","id":60919433}],"symbols":[]},"id_str":"1223263743473332224","in_reply_to_user_id":60919433,"favorite_count":0,"id":1223263743473332224,"text":"@lizardbill Not something I really did in the first place...","place":null,"contributors":null,"lang":"en","user":{"utc_offset":null,"friends_count":716,"profile_image_url_https":"https://pbs.twimg.com/profile_images/1108023173319180289/0kJImc2D_normal.png","listed_count":20,"profile_background_image_url":"http://abs.twimg.com/images/themes/theme9/bg.gif","default_profile_image":false,"favourites_count":3895,"description":"Code monkey, board gamer and procrastinator. Shawarma enthusiast. Just a node in a galaxy spanning arachnid hive mind. He/Him","created_at":"Fri Dec 01 12:09:57 +0000 2006","is_translator":false,"profile_background_image_url_https":"https://abs.twimg.com/images/themes/theme9/bg.gif","protected":false,"screen_name":"ohmz","id_str":"33893","profile_link_color":"2FC2EF","is_translation_enabled":false,"translator_type":"none","id":33893,"geo_enabled":true,"profile_background_color":"1A1B1F","lang":null,"has_extended_profile":true,"profile_sidebar_border_color":"181A1E","profile_text_color":"666666","verified":false,"profile_image_url":"http://pbs.twimg.com/profile_images/1108023173319180289/0kJImc2D_normal.png","time_zone":null,"url":"https://t.co/rQYiK5640G","contributors_enabled":false,"profile_background_tile":false,"profile_banner_url":"https://pbs.twimg.com/profile_banners/33893/1353325644","entities":{"description":{"urls":[]},"url":{"urls":[{"display_url":"ohmz.net","indices":[0,23],"expanded_url":"http://www.ohmz.net","url":"https://t.co/rQYiK5640G"}]}},"statuses_count":30446,"follow_request_sent":false,"followers_count":463,"profile_use_background_image":true,"default_profile":false,"following":false,"name":"Omar Kooheji (I don't have time for a clever name)","location":"Glasgow","profile_sidebar_fill_color":"252429","notifications":false},"favorited":false}, {"metadata":{"result_type":"recent","iso_language_code":"und"},"in_reply_to_status_id_str":"1223242285342711809","in_reply_to_status_id":1223242285342711809,"created_at":"Fri Jan 31 13:58:00 +0000 2020","in_reply_to_user_id_str":"60919433","source":"<a href=\"https://mobile.twitter.com\" rel=\"nofollow\">Twitter Web App<\/a>","retweet_count":0,"retweeted":false,"geo":null,"in_reply_to_screen_name":"lizardbill","is_quote_status":false,"id_str":"1223244038918287360","in_reply_to_user_id":60919433,"favorite_count":1,"id":1223244038918287360,"text":"@lizardbill https://t.co/d6XhvDSbK1","place":null,"lang":"und","favorited":false,"possibly_sensitive":false,"coordinates":null,"truncated":false,"entities":{"urls":[{"display_url":"youtube.com/watch?v=9rvVug\u2026","indices":[12,35],"expanded_url":"https://www.youtube.com/watch?v=9rvVugY-kZc","url":"https://t.co/d6XhvDSbK1"}],"hashtags":[],"user_mentions":[{"indices":[0,11],"screen_name":"lizardbill","id_str":"60919433","name":"Bill the Lizard","id":60919433}],"symbols":[]},"contributors":null,"user":{"utc_offset":null,"friends_count":413,"profile_image_url_https":"https://pbs.twimg.com/profile_images/1022825657573695489/6LoBYlQg_normal.jpg","listed_count":69,"profile_background_image_url":"http://abs.twimg.com/images/themes/theme1/bg.png","default_profile_image":false,"favourites_count":12576,"description":"Chaotic Good w a splash of Data. Dad x2. Stack Overflow. He/him. https://t.co/LYifYPgRnX","created_at":"Fri Apr 11 20:31:19 +0000 2008","is_translator":false,"profile_background_image_url_https":"https://abs.twimg.com/images/themes/theme1/bg.png","protected":false,"screen_name":"JasonPunyon","id_str":"14364352","profile_link_color":"E2C5AD","is_translation_enabled":false,"translator_type":"none","id":14364352,"geo_enabled":false,"profile_background_color":"FFFFFF","lang":null,"has_extended_profile":false,"profile_sidebar_border_color":"BDDCAD","profile_text_color":"333333","verified":false,"profile_image_url":"http://pbs.twimg.com/profile_images/1022825657573695489/6LoBYlQg_normal.jpg","time_zone":null,"url":null,"contributors_enabled":false,"profile_background_tile":false,"entities":{"description":{"urls":[{"display_url":"jasonpunyon.com","indices":[65,88],"expanded_url":"http://jasonpunyon.com","url":"https://t.co/LYifYPgRnX"}]}},"statuses_count":22932,"follow_request_sent":false,"followers_count":1784,"profile_use_background_image":false,"default_profile":false,"following":false,"name":"🥣 making more soup 🥣","location":"","profile_sidebar_fill_color":"FFFFFF","notifications":false}}, {"metadata":{"result_type":"recent","iso_language_code":"en"},"in_reply_to_status_id_str":null,"in_reply_to_status_id":null,"coordinates":null,"created_at":"Fri Jan 31 13:51:02 +0000 2020","truncated":false,"in_reply_to_user_id_str":null,"source":"<a href=\"https://mobile.twitter.com\" rel=\"nofollow\">Twitter Web App<\/a>","retweet_count":0,"retweeted":false,"geo":null,"in_reply_to_screen_name":null,"is_quote_status":false,"entities":{"urls":[],"hashtags":[],"user_mentions":[],"symbols":[]},"id_str":"1223242285342711809","in_reply_to_user_id":null,"favorite_count":5,"id":1223242285342711809,"text":"Overnight oats is asking me to make a decision way too far in advance.","place":null,"contributors":null,"lang":"en","user":{"utc_offset":null,"friends_count":695,"profile_image_url_https":"https://pbs.twimg.com/profile_images/2316539047/y13vrqqe257qh7h9erb9_normal.png","listed_count":243,"profile_background_image_url":"http://abs.twimg.com/images/themes/theme1/bg.png","default_profile_image":false,"favourites_count":28740,"description":"Professional Software Developer. Amateur Futurist and Chart Critic. Math Enthusiast. I write static code analysis tools and 1st drafts of blog posts. he/him","created_at":"Tue Jul 28 14:37:29 +0000 2009","is_translator":false,"profile_background_image_url_https":"https://abs.twimg.com/images/themes/theme1/bg.png","protected":false,"screen_name":"lizardbill","id_str":"60919433","profile_link_color":"0E6E20","is_translation_enabled":false,"translator_type":"none","id":60919433,"geo_enabled":true,"profile_background_color":"9AC295","lang":null,"has_extended_profile":false,"profile_sidebar_border_color":"C7EDCC","profile_text_color":"543920","verified":false,"profile_image_url":"http://pbs.twimg.com/profile_images/2316539047/y13vrqqe257qh7h9erb9_normal.png","time_zone":null,"url":"https://t.co/ZJdVLoKjKc","contributors_enabled":false,"profile_background_tile":false,"profile_banner_url":"https://pbs.twimg.com/profile_banners/60919433/1542989249","entities":{"description":{"urls":[]},"url":{"urls":[{"display_url":"BillTheLizard.blogspot.com","indices":[0,23],"expanded_url":"http://www.BillTheLizard.blogspot.com","url":"https://t.co/ZJdVLoKjKc"}]}},"statuses_count":19279,"follow_request_sent":false,"followers_count":5315,"profile_use_background_image":false,"default_profile":false,"following":false,"name":"Bill the Lizard","location":"Charlotte, NC USA","profile_sidebar_fill_color":"9DD4A9","notifications":false},"favorited":false}, {"metadata":{"result_type":"recent","iso_language_code":"en"},"in_reply_to_status_id_str":"1223234297823408128","in_reply_to_status_id":1223234297823408128,"coordinates":null,"created_at":"Fri Jan 31 13:36:59 +0000 2020","truncated":false,"in_reply_to_user_id_str":"60919433","source":"<a href=\"https://mobile.twitter.com\" rel=\"nofollow\">Twitter Web App<\/a>","retweet_count":0,"retweeted":false,"geo":null,"in_reply_to_screen_name":"lizardbill","is_quote_status":false,"entities":{"urls":[],"hashtags":[],"user_mentions":[{"indices":[0,11],"screen_name":"lizardbill","id_str":"60919433","name":"Bill the Lizard","id":60919433},{"indices":[12,17],"screen_name":"ohmz","id_str":"33893","name":"Omar Kooheji (I don't have time for a clever name)","id":33893}],"symbols":[]},"id_str":"1223238750492340226","in_reply_to_user_id":60919433,"favorite_count":1,"id":1223238750492340226,"text":"@lizardbill @ohmz That alone arguably made it worthwhile","place":null,"contributors":null,"lang":"en","user":{"utc_offset":null,"friends_count":436,"profile_image_url_https":"https://pbs.twimg.com/profile_images/1006818081862291459/vmM3KP5S_normal.jpg","listed_count":1,"profile_background_image_url":"http://abs.twimg.com/images/themes/theme1/bg.png","default_profile_image":false,"favourites_count":54754,"description":"🇩🇪🇫🇮, live in 🇪🇸🇮🇨. Anglophile 🇺🇸🇬🇧. WebDev, graphic design & an old off-the-grid house by ☀️, politics & culture during breaks, art & visual storytelling by 🌜.","created_at":"Fri Mar 23 22:41:16 +0000 2018","is_translator":false,"profile_background_image_url_https":"https://abs.twimg.com/images/themes/theme1/bg.png","protected":false,"screen_name":"pekkagaiser","id_str":"977314361952866306","profile_link_color":"336666","is_translation_enabled":false,"translator_type":"none","id":977314361952866306,"geo_enabled":false,"profile_background_color":"000000","lang":null,"has_extended_profile":false,"profile_sidebar_border_color":"000000","profile_text_color":"000000","verified":false,"profile_image_url":"http://pbs.twimg.com/profile_images/1006818081862291459/vmM3KP5S_normal.jpg","time_zone":null,"url":"https://t.co/Liir0lAVxY","contributors_enabled":false,"profile_background_tile":false,"profile_banner_url":"https://pbs.twimg.com/profile_banners/977314361952866306/1551776975","entities":{"description":{"urls":[]},"url":{"urls":[{"display_url":"pekka.net","indices":[0,23],"expanded_url":"http://www.pekka.net/","url":"https://t.co/Liir0lAVxY"}]}},"statuses_count":5665,"follow_request_sent":false,"followers_count":265,"profile_use_background_image":false,"default_profile":false,"following":false,"name":"Pekka","location":"Lanzarote, Canary Islands","profile_sidebar_fill_color":"000000","notifications":false},"favorited":false}, {"metadata":{"result_type":"recent","iso_language_code":"en"},"in_reply_to_status_id_str":"1223219338896912384","in_reply_to_status_id":1223219338896912384,"coordinates":null,"created_at":"Fri Jan 31 13:19:17 +0000 2020","truncated":false,"in_reply_to_user_id_str":"33893","source":"<a href=\"https://mobile.twitter.com\" rel=\"nofollow\">Twitter Web App<\/a>","retweet_count":0,"retweeted":false,"geo":null,"in_reply_to_screen_name":"ohmz","is_quote_status":false,"entities":{"urls":[],"hashtags":[],"user_mentions":[{"indices":[0,5],"screen_name":"ohmz","id_str":"33893","name":"Omar Kooheji (I don't have time for a clever name)","id":33893}],"symbols":[]},"id_str":"1223234297823408128","in_reply_to_user_id":33893,"favorite_count":2,"id":1223234297823408128,"text":"@ohmz You have to stop watching Eurovision too. Sorry.","place":null,"contributors":null,"lang":"en","user":{"utc_offset":null,"friends_count":695,"profile_image_url_https":"https://pbs.twimg.com/profile_images/2316539047/y13vrqqe257qh7h9erb9_normal.png","listed_count":243,"profile_background_image_url":"http://abs.twimg.com/images/themes/theme1/bg.png","default_profile_image":false,"favourites_count":28740,"description":"Professional Software Developer. Amateur Futurist and Chart Critic. Math Enthusiast. I write static code analysis tools and 1st drafts of blog posts. he/him","created_at":"Tue Jul 28 14:37:29 +0000 2009","is_translator":false,"profile_background_image_url_https":"https://abs.twimg.com/images/themes/theme1/bg.png","protected":false,"screen_name":"lizardbill","id_str":"60919433","profile_link_color":"0E6E20","is_translation_enabled":false,"translator_type":"none","id":60919433,"geo_enabled":true,"profile_background_color":"9AC295","lang":null,"has_extended_profile":false,"profile_sidebar_border_color":"C7EDCC","profile_text_color":"543920","verified":false,"profile_image_url":"http://pbs.twimg.com/profile_images/2316539047/y13vrqqe257qh7h9erb9_normal.png","time_zone":null,"url":"https://t.co/ZJdVLoKjKc","contributors_enabled":false,"profile_background_tile":false,"profile_banner_url":"https://pbs.twimg.com/profile_banners/60919433/1542989249","entities":{"description":{"urls":[]},"url":{"urls":[{"display_url":"BillTheLizard.blogspot.com","indices":[0,23],"expanded_url":"http://www.BillTheLizard.blogspot.com","url":"https://t.co/ZJdVLoKjKc"}]}},"statuses_count":19279,"follow_request_sent":false,"followers_count":5315,"profile_use_background_image":false,"default_profile":false,"following":false,"name":"Bill the Lizard","location":"Charlotte, NC USA","profile_sidebar_fill_color":"9DD4A9","notifications":false},"favorited":false}, {"metadata":{"result_type":"recent","iso_language_code":"en"},"in_reply_to_status_id_str":"1222690181460963328","in_reply_to_status_id":1222690181460963328,"coordinates":null,"created_at":"Thu Jan 30 18:56:58 +0000 2020","truncated":false,"in_reply_to_user_id_str":"75604826","source":"<a href=\"https://mobile.twitter.com\" rel=\"nofollow\">Twitter Web App<\/a>","retweet_count":0,"retweeted":false,"geo":null,"in_reply_to_screen_name":"GraceSpelman","is_quote_status":false,"entities":{"urls":[],"hashtags":[],"user_mentions":[{"indices":[0,13],"screen_name":"GraceSpelman","id_str":"75604826","name":"Grace Spelman","id":75604826}],"symbols":[]},"id_str":"1222956887601270784","in_reply_to_user_id":75604826,"favorite_count":0,"id":1222956887601270784,"text":"@GraceSpelman How do I sign up for this newsletter?","place":null,"contributors":null,"lang":"en","user":{"utc_offset":null,"friends_count":695,"profile_image_url_https":"https://pbs.twimg.com/profile_images/2316539047/y13vrqqe257qh7h9erb9_normal.png","listed_count":243,"profile_background_image_url":"http://abs.twimg.com/images/themes/theme1/bg.png","default_profile_image":false,"favourites_count":28740,"description":"Professional Software Developer. Amateur Futurist and Chart Critic. Math Enthusiast. I write static code analysis tools and 1st drafts of blog posts. he/him","created_at":"Tue Jul 28 14:37:29 +0000 2009","is_translator":false,"profile_background_image_url_https":"https://abs.twimg.com/images/themes/theme1/bg.png","protected":false,"screen_name":"lizardbill","id_str":"60919433","profile_link_color":"0E6E20","is_translation_enabled":false,"translator_type":"none","id":60919433,"geo_enabled":true,"profile_background_color":"9AC295","lang":null,"has_extended_profile":false,"profile_sidebar_border_color":"C7EDCC","profile_text_color":"543920","verified":false,"profile_image_url":"http://pbs.twimg.com/profile_images/2316539047/y13vrqqe257qh7h9erb9_normal.png","time_zone":null,"url":"https://t.co/ZJdVLoKjKc","contributors_enabled":false,"profile_background_tile":false,"profile_banner_url":"https://pbs.twimg.com/profile_banners/60919433/1542989249","entities":{"description":{"urls":[]},"url":{"urls":[{"display_url":"BillTheLizard.blogspot.com","indices":[0,23],"expanded_url":"http://www.BillTheLizard.blogspot.com","url":"https://t.co/ZJdVLoKjKc"}]}},"statuses_count":19279,"follow_request_sent":false,"followers_count":5315,"profile_use_background_image":false,"default_profile":false,"following":false,"name":"Bill the Lizard","location":"Charlotte, NC USA","profile_sidebar_fill_color":"9DD4A9","notifications":false},"favorited":false}, {"metadata":{"result_type":"recent","iso_language_code":"en"},"in_reply_to_status_id_str":null,"in_reply_to_status_id":null,"coordinates":null,"created_at":"Thu Jan 30 18:44:36 +0000 2020","truncated":false,"in_reply_to_user_id_str":null,"source":"<a href=\"https://mobile.twitter.com\" rel=\"nofollow\">Twitter Web App<\/a>","retweet_count":0,"retweeted":false,"geo":null,"in_reply_to_screen_name":null,"is_quote_status":false,"entities":{"urls":[],"hashtags":[],"user_mentions":[],"symbols":[]},"id_str":"1222953778107813889","in_reply_to_user_id":null,"favorite_count":1,"id":1222953778107813889,"text":"The Iowa caucus is in 4 days. Where are all the \"caucus\" puns?","place":null,"contributors":null,"lang":"en","user":{"utc_offset":null,"friends_count":695,"profile_image_url_https":"https://pbs.twimg.com/profile_images/2316539047/y13vrqqe257qh7h9erb9_normal.png","listed_count":243,"profile_background_image_url":"http://abs.twimg.com/images/themes/theme1/bg.png","default_profile_image":false,"favourites_count":28740,"description":"Professional Software Developer. Amateur Futurist and Chart Critic. Math Enthusiast. I write static code analysis tools and 1st drafts of blog posts. he/him","created_at":"Tue Jul 28 14:37:29 +0000 2009","is_translator":false,"profile_background_image_url_https":"https://abs.twimg.com/images/themes/theme1/bg.png","protected":false,"screen_name":"lizardbill","id_str":"60919433","profile_link_color":"0E6E20","is_translation_enabled":false,"translator_type":"none","id":60919433,"geo_enabled":true,"profile_background_color":"9AC295","lang":null,"has_extended_profile":false,"profile_sidebar_border_color":"C7EDCC","profile_text_color":"543920","verified":false,"profile_image_url":"http://pbs.twimg.com/profile_images/2316539047/y13vrqqe257qh7h9erb9_normal.png","time_zone":null,"url":"https://t.co/ZJdVLoKjKc","contributors_enabled":false,"profile_background_tile":false,"profile_banner_url":"https://pbs.twimg.com/profile_banners/60919433/1542989249","entities":{"description":{"urls":[]},"url":{"urls":[{"display_url":"BillTheLizard.blogspot.com","indices":[0,23],"expanded_url":"http://www.BillTheLizard.blogspot.com","url":"https://t.co/ZJdVLoKjKc"}]}},"statuses_count":19279,"follow_request_sent":false,"followers_count":5315,"profile_use_background_image":false,"default_profile":false,"following":false,"name":"Bill the Lizard","location":"Charlotte, NC USA","profile_sidebar_fill_color":"9DD4A9","notifications":false},"favorited":false}, {"metadata":{"result_type":"recent","iso_language_code":"en"},"in_reply_to_status_id_str":"1222936321615978496","in_reply_to_status_id":1222936321615978496,"coordinates":null,"created_at":"Thu Jan 30 18:11:10 +0000 2020","truncated":false,"in_reply_to_user_id_str":"60919433","source":"<a href=\"https://mobile.twitter.com\" rel=\"nofollow\">Twitter Web App<\/a>","retweet_count":0,"retweeted":false,"geo":null,"in_reply_to_screen_name":"lizardbill","is_quote_status":false,"entities":{"urls":[],"hashtags":[],"user_mentions":[{"indices":[0,11],"screen_name":"lizardbill","id_str":"60919433","name":"Bill the Lizard","id":60919433}],"symbols":[]},"id_str":"1222945364698898433","in_reply_to_user_id":60919433,"favorite_count":2,"id":1222945364698898433,"text":"@lizardbill Ahh, the dreaded plateau. I know the feeling. 🙂","place":null,"contributors":null,"lang":"en","user":{"utc_offset":null,"friends_count":323,"profile_image_url_https":"https://pbs.twimg.com/profile_images/2187168864/gravatar_blue_normal.png","listed_count":60,"profile_background_image_url":"http://abs.twimg.com/images/themes/theme5/bg.gif","default_profile_image":false,"favourites_count":39238,"description":"Likes: patterns, writing code, skepticism, astronomy. Atheist with zero bullshit tolerance. Tweets: EN, DE, 日本語 (勉強中).","created_at":"Wed Jun 25 08:05:24 +0000 2008","is_translator":false,"profile_background_image_url_https":"https://abs.twimg.com/images/themes/theme5/bg.gif","protected":false,"screen_name":"_Tomalak","id_str":"15228808","profile_link_color":"0281CC","is_translation_enabled":false,"translator_type":"regular","id":15228808,"geo_enabled":true,"profile_background_color":"19458C","lang":null,"has_extended_profile":false,"profile_sidebar_border_color":"000000","profile_text_color":"72C6D9","verified":false,"profile_image_url":"http://pbs.twimg.com/profile_images/2187168864/gravatar_blue_normal.png","time_zone":null,"url":"http://t.co/QHMGCAllUT","contributors_enabled":false,"profile_background_tile":false,"profile_banner_url":"https://pbs.twimg.com/profile_banners/15228808/1398196803","entities":{"description":{"urls":[]},"url":{"urls":[{"display_url":"stackoverflow.com/users/18771/to\u2026","indices":[0,22],"expanded_url":"http://stackoverflow.com/users/18771/tomalak","url":"http://t.co/QHMGCAllUT"}]}},"statuses_count":73512,"follow_request_sent":false,"followers_count":709,"profile_use_background_image":true,"default_profile":false,"following":false,"name":"Tomalak","location":"Frankfurt, Germany","profile_sidebar_fill_color":"2C3E42","notifications":false},"favorited":false}, {"metadata":{"result_type":"recent","iso_language_code":"en"},"in_reply_to_status_id_str":"1222934950091067393","in_reply_to_status_id":1222934950091067393,"coordinates":null,"created_at":"Thu Jan 30 17:54:36 +0000 2020","truncated":false,"in_reply_to_user_id_str":"60919433","source":"<a href=\"http://twitter.com/download/android\" rel=\"nofollow\">Twitter for Android<\/a>","retweet_count":0,"retweeted":false,"geo":null,"in_reply_to_screen_name":"lizardbill","is_quote_status":false,"entities":{"urls":[],"hashtags":[],"user_mentions":[{"indices":[0,11],"screen_name":"lizardbill","id_str":"60919433","name":"Bill the Lizard","id":60919433}],"symbols":[]},"id_str":"1222941195250257920","in_reply_to_user_id":60919433,"favorite_count":1,"id":1222941195250257920,"text":"@lizardbill He wasn't referring to JavaScript, Bill","place":null,"contributors":null,"lang":"en","user":{"utc_offset":null,"friends_count":599,"profile_image_url_https":"https://pbs.twimg.com/profile_images/1094681130991636481/QNaiODBL_normal.jpg","listed_count":64,"profile_background_image_url":"http://abs.twimg.com/images/themes/theme13/bg.gif","default_profile_image":false,"favourites_count":58326,"description":"Geeky yet palatable\u2026 \n● I do tech stuff @CrowdStrike w/#golang \n● I have a wife & 2 daughters (thing one & thing two) \n● erraggy = how Scooby-Doo says Shaggy","created_at":"Fri Mar 23 20:14:12 +0000 2007","is_translator":false,"profile_background_image_url_https":"https://abs.twimg.com/images/themes/theme13/bg.gif","protected":false,"screen_name":"erraggy","id_str":"2048331","profile_link_color":"93A644","is_translation_enabled":false,"translator_type":"none","id":2048331,"geo_enabled":true,"profile_background_color":"B2DFDA","lang":null,"has_extended_profile":true,"profile_sidebar_border_color":"EEEEEE","profile_text_color":"333333","verified":false,"profile_image_url":"http://pbs.twimg.com/profile_images/1094681130991636481/QNaiODBL_normal.jpg","time_zone":null,"url":"https://t.co/z8sz9hnHYu","contributors_enabled":false,"profile_background_tile":false,"profile_banner_url":"https://pbs.twimg.com/profile_banners/2048331/1399418159","entities":{"description":{"urls":[]},"url":{"urls":[{"display_url":"about.me/robbie.coleman","indices":[0,23],"expanded_url":"https://about.me/robbie.coleman","url":"https://t.co/z8sz9hnHYu"}]}},"statuses_count":40692,"follow_request_sent":false,"followers_count":1636,"profile_use_background_image":true,"default_profile":false,"following":false,"name":"Robbie Coleman","location":"opinions are my own, L.A., CA","profile_sidebar_fill_color":"FFFFFF","notifications":false},"favorited":false}, {"metadata":{"result_type":"recent","iso_language_code":"en"},"quoted_status":{"metadata":{"result_type":"recent","iso_language_code":"en"},"in_reply_to_status_id_str":null,"in_reply_to_status_id":null,"coordinates":null,"created_at":"Thu Jan 30 17:29:47 +0000 2020","truncated":false,"in_reply_to_user_id_str":null,"source":"<a href=\"https://mobile.twitter.com\" rel=\"nofollow\">Twitter Web App<\/a>","retweet_count":2,"retweeted":false,"geo":null,"in_reply_to_screen_name":null,"is_quote_status":false,"entities":{"urls":[],"hashtags":[],"user_mentions":[],"symbols":[]},"id_str":"1222934950091067393","in_reply_to_user_id":null,"favorite_count":9,"id":1222934950091067393,"text":"\"To have another language is to possess a second soul.\"\n-Charlemagne","place":null,"contributors":null,"lang":"en","user":{"utc_offset":null,"friends_count":695,"profile_image_url_https":"https://pbs.twimg.com/profile_images/2316539047/y13vrqqe257qh7h9erb9_normal.png","listed_count":243,"profile_background_image_url":"http://abs.twimg.com/images/themes/theme1/bg.png","default_profile_image":false,"favourites_count":28740,"description":"Professional Software Developer. Amateur Futurist and Chart Critic. Math Enthusiast. I write static code analysis tools and 1st drafts of blog posts. he/him","created_at":"Tue Jul 28 14:37:29 +0000 2009","is_translator":false,"profile_background_image_url_https":"https://abs.twimg.com/images/themes/theme1/bg.png","protected":false,"screen_name":"lizardbill","id_str":"60919433","profile_link_color":"0E6E20","is_translation_enabled":false,"translator_type":"none","id":60919433,"geo_enabled":true,"profile_background_color":"9AC295","lang":null,"has_extended_profile":false,"profile_sidebar_border_color":"C7EDCC","profile_text_color":"543920","verified":false,"profile_image_url":"http://pbs.twimg.com/profile_images/2316539047/y13vrqqe257qh7h9erb9_normal.png","time_zone":null,"url":"https://t.co/ZJdVLoKjKc","contributors_enabled":false,"profile_background_tile":false,"profile_banner_url":"https://pbs.twimg.com/profile_banners/60919433/1542989249","entities":{"description":{"urls":[]},"url":{"urls":[{"display_url":"BillTheLizard.blogspot.com","indices":[0,23],"expanded_url":"http://www.BillTheLizard.blogspot.com","url":"https://t.co/ZJdVLoKjKc"}]}},"statuses_count":19279,"follow_request_sent":false,"followers_count":5315,"profile_use_background_image":false,"default_profile":false,"following":false,"name":"Bill the Lizard","location":"Charlotte, NC USA","profile_sidebar_fill_color":"9DD4A9","notifications":false},"favorited":false},"in_reply_to_status_id_str":null,"in_reply_to_status_id":null,"created_at":"Thu Jan 30 17:50:53 +0000 2020","in_reply_to_user_id_str":null,"source":"<a href=\"http://twitter.com/download/iphone\" rel=\"nofollow\">Twitter for iPhone<\/a>","quoted_status_id":1222934950091067393,"retweet_count":0,"retweeted":false,"geo":null,"in_reply_to_screen_name":null,"is_quote_status":true,"id_str":"1222940258121043968","in_reply_to_user_id":null,"favorite_count":0,"id":1222940258121043968,"text":"This is why you should know dozens of different programming languages. https://t.co/MLb4HD8QAV","place":null,"lang":"en","favorited":false,"possibly_sensitive":false,"coordinates":null,"truncated":false,"entities":{"urls":[{"display_url":"twitter.com/lizardbill/sta\u2026","indices":[71,94],"expanded_url":"https://twitter.com/lizardbill/status/1222934950091067393","url":"https://t.co/MLb4HD8QAV"}],"hashtags":[],"user_mentions":[],"symbols":[]},"quoted_status_id_str":"1222934950091067393","contributors":null,"user":{"utc_offset":null,"friends_count":405,"profile_image_url_https":"https://pbs.twimg.com/profile_images/925013528305475584/ijUXvw6P_normal.jpg","listed_count":61,"profile_background_image_url":"http://abs.twimg.com/images/themes/theme9/bg.gif","default_profile_image":false,"favourites_count":620,"description":"Polyglot Polymath he/him who loves making the world better via #leadership and #Integrity. Blunt out of #Love and #infosec. Views are own and not my employers.","created_at":"Tue Jun 21 00:04:25 +0000 2011","is_translator":false,"profile_background_image_url_https":"https://abs.twimg.com/images/themes/theme9/bg.gif","protected":false,"screen_name":"honestduane","id_str":"321070496","profile_link_color":"3B94D9","is_translation_enabled":false,"translator_type":"none","id":321070496,"geo_enabled":false,"profile_background_color":"000000","lang":null,"has_extended_profile":false,"profile_sidebar_border_color":"000000","profile_text_color":"000000","verified":false,"profile_image_url":"http://pbs.twimg.com/profile_images/925013528305475584/ijUXvw6P_normal.jpg","time_zone":null,"url":"https://t.co/JHxxwMiJDw","contributors_enabled":false,"profile_background_tile":false,"profile_banner_url":"https://pbs.twimg.com/profile_banners/321070496/1420417967","entities":{"description":{"urls":[]},"url":{"urls":[{"display_url":"keybase.io/dfk","indices":[0,23],"expanded_url":"http://www.keybase.io/dfk","url":"https://t.co/JHxxwMiJDw"}]}},"statuses_count":14876,"follow_request_sent":false,"followers_count":385,"profile_use_background_image":false,"default_profile":false,"following":false,"name":"(((Duane))) - 🧙\u200d♂️🖖🦁- Hire Me!","location":"Seattle, WA, USA","profile_sidebar_fill_color":"000000","notifications":false}}]